MANIFEST.in
README.rst
requirements.txt
setup.py
nested_lookup/__init__.py
nested_lookup/lookup_api.py
nested_lookup/nested_lookup.py
nested_lookup.egg-info/PKG-INFO
nested_lookup.egg-info/SOURCES.txt
nested_lookup.egg-info/dependency_links.txt
nested_lookup.egg-info/top_level.txt