Metadata-Version: 1.1
Name: nested-lookup
Version: 0.2.15
Summary: Python functions for working with deeply nested documents (lists and dicts) 
Home-page: https://github.com/russellballestrini/nested-lookup
Author: Russell Ballestrini
Author-email: russell@ballestrini.net
License: Public Domain
Keywords: nested document dictionary dict list lookup schema json xml yaml
Platform: All
Classifier: Programming Language :: Python :: 2.6
Classifier: Programming Language :: Python :: 2.7
Classifier: Programming Language :: Python :: 3.5
Classifier: Programming Language :: Python :: 3.6
Classifier: Programming Language :: Python :: 3.7
